pg_database/__init__.py
pg_database/conf.py
pg_database/schema.py
pg_database/sql.py
pg_database/tests/__init__.py
pg_database/tests/custom_databases.json
pg_database/tests/custom_databases.py
pg_database/tests/invalid_config.json
pg_database/tests/invalid_settings.py
pg_database/tests/missing_django_db.json
pg_database/tests/missing_django_db.py
pg_database/tests/not.json
pg_database/tests/not_settings.py
pg_database/tests/settings.py
pg_database/tests/test_config.json
pg_database/tests/tests.py
pg_database/types.py
pg_database/validation.py
pg_database_utils-1.0.0.dist-info/LICENSE
pg_database_utils-1.0.0.dist-info/METADATA
pg_database_utils-1.0.0.dist-info/WHEEL
pg_database_utils-1.0.0.dist-info/RECORD
