Metadata-Version: 2.1
Name: pg-database-utils
Version: 1.0.0
Summary: A suite of utilities for PostgreSQL database queries and operations built on sqlalchemy
Home-page: https://github.com/consbio/pg-database-utils/
License: BSD
Keywords: postgres,postgresql,utils,utilities,pg_database,pg_database_utils,sqlalchemy
Author: dharvey-consbio
Author-email: dani.harvey@consbio.org
Requires-Python: >=3.9,<4.0
Classifier: License :: Other/Proprietary License
Classifier: Programming Language :: Python :: 3
Classifier: Programming Language :: Python :: 3.9
Classifier: Programming Language :: Python :: 3.10
Classifier: Programming Language :: Python :: 3.11
Classifier: Programming Language :: Python :: 3.12
Requires-Dist: GeoAlchemy2
Requires-Dist: frozendict (>=2.3.8,<3.0.0)
Requires-Dist: psycopg2-binary (>=2.7.7,<3.0.0)
Requires-Dist: sqlalchemy (>=1.4.49,<2.0.0)
Project-URL: Repository, https://github.com/consbio/pg-database-utils/
